raplan/__init__.py
raplan/analysis.py
raplan/classes.py
raplan/distributions.py
raplan/excel.py
raplan/plot.py
raplan/py.typed
raplan/yaml.py
raplan-0.9.9.dist-info/METADATA
raplan-0.9.9.dist-info/WHEEL
raplan-0.9.9.dist-info/licenses/LICENSE.md
raplan-0.9.9.dist-info/RECORD
