Metadata-Version: 2.4
Name: raplan
Version: 0.9.9
Summary: Ratio maintenance planning and scheduling in Python.
Project-URL: Homepage, https://raplan.ratio-case.nl
Project-URL: Repository, https://gitlab.com/ratio-case-os/python/raplan
Project-URL: Bug Tracker, https://gitlab.com/ratio-case-os/python/raplan/-/issues
Project-URL: Changelog, https://raplan.ratio-case.nl/CHANGELOG/
Author-email: "Ratio Innovations B.V." <info@ratio-case.nl>
License-Expression: GPL-3.0-or-later
License-File: LICENSE.md
Keywords: distribution,planning,scheduling,visualisation,visualization
Requires-Python: >=3.11
Requires-Dist: pyserde[yaml]>=0.23.0
Provides-Extra: all
Requires-Dist: kaleido==0.2.1; extra == 'all'
Requires-Dist: openpyxl>=3.1.5; extra == 'all'
Requires-Dist: plotly>=6.0.0; extra == 'all'
Requires-Dist: ragraph>=1.22.7; extra == 'all'
Provides-Extra: analysis
Requires-Dist: ragraph>=1.22.7; extra == 'analysis'
Provides-Extra: excel
Requires-Dist: openpyxl>=3.1.5; extra == 'excel'
Provides-Extra: plot
Requires-Dist: kaleido==0.2.1; extra == 'plot'
Requires-Dist: plotly>=6.0.0; extra == 'plot'
